dbnomics_fetcher_toolbox/__init__.py
dbnomics_fetcher_toolbox/aiohttp_utils.py
dbnomics_fetcher_toolbox/arguments.py
dbnomics_fetcher_toolbox/cli.py
dbnomics_fetcher_toolbox/data_model.py
dbnomics_fetcher_toolbox/file_system_utils.py
dbnomics_fetcher_toolbox/formats.py
dbnomics_fetcher_toolbox/logging_utils.py
dbnomics_fetcher_toolbox/parts.py
dbnomics_fetcher_toolbox/resources.py
dbnomics_fetcher_toolbox/sdmx_v2_0.py
dbnomics_fetcher_toolbox/status.py
dbnomics_fetcher_toolbox/utils.py
dbnomics_fetcher_toolbox-0.0.9.dist-info/LICENSE
dbnomics_fetcher_toolbox-0.0.9.dist-info/METADATA
dbnomics_fetcher_toolbox-0.0.9.dist-info/WHEEL
dbnomics_fetcher_toolbox-0.0.9.dist-info/entry_points.txt
dbnomics_fetcher_toolbox-0.0.9.dist-info/top_level.txt
dbnomics_fetcher_toolbox-0.0.9.dist-info/RECORD
